GoMegaJiaocheng/README.md
GoMegaJiaocheng/__init__.py
GoMegaJiaocheng/__main__.py
GoMegaJiaocheng/file.epub
GoMegaJiaocheng/index.html
GoMegaJiaocheng/css/__init__.py
GoMegaJiaocheng/css/annotations.css
GoMegaJiaocheng/css/main.css
GoMegaJiaocheng/css/normalize.css
GoMegaJiaocheng/css/popup.css
GoMegaJiaocheng/font/__init__.py
GoMegaJiaocheng/font/fontello.eot
GoMegaJiaocheng/font/fontello.svg
GoMegaJiaocheng/font/fontello.ttf
GoMegaJiaocheng/font/fontello.woff
GoMegaJiaocheng/img/__init__.py
GoMegaJiaocheng/img/annotator-glyph-sprite.png
GoMegaJiaocheng/img/annotator-icon-sprite.png
GoMegaJiaocheng/img/apple-touch-icon.png
GoMegaJiaocheng/img/cancelfullscreen.png
GoMegaJiaocheng/img/close.png
GoMegaJiaocheng/img/fullscreen.png
GoMegaJiaocheng/img/loader.gif
GoMegaJiaocheng/img/menu-icon.png
GoMegaJiaocheng/img/save.png
GoMegaJiaocheng/img/saved.png
GoMegaJiaocheng/img/settings-s.png
GoMegaJiaocheng/img/settings.png
GoMegaJiaocheng/img/star.png
GoMegaJiaocheng/js/__init__.py
GoMegaJiaocheng/js/epub.js
GoMegaJiaocheng/js/epub.min.js
GoMegaJiaocheng/js/epub.min.map
GoMegaJiaocheng/js/hooks.min.js
GoMegaJiaocheng/js/hooks.min.map
GoMegaJiaocheng/js/reader.js
GoMegaJiaocheng/js/reader.js.map
GoMegaJiaocheng/js/reader.min.js
GoMegaJiaocheng/js/reader.min.map
GoMegaJiaocheng/js/hooks/__init__.py
GoMegaJiaocheng/js/hooks/extensions/__init__.py
GoMegaJiaocheng/js/hooks/extensions/highlight.js
GoMegaJiaocheng/js/libs/__init__.py
GoMegaJiaocheng/js/libs/jquery.min.js
GoMegaJiaocheng/js/libs/localforage.min.js
GoMegaJiaocheng/js/libs/screenfull.js
GoMegaJiaocheng/js/libs/screenfull.min.js
GoMegaJiaocheng/js/libs/zip.min.js
GoMegaJiaocheng/js/plugins/__init__.py
GoMegaJiaocheng/js/plugins/hypothesis.js
GoMegaJiaocheng/js/plugins/search.js
go_mega_jiaocheng-2024.3.5.0.dist-info/METADATA
go_mega_jiaocheng-2024.3.5.0.dist-info/WHEEL
go_mega_jiaocheng-2024.3.5.0.dist-info/entry_points.txt
go_mega_jiaocheng-2024.3.5.0.dist-info/top_level.txt
go_mega_jiaocheng-2024.3.5.0.dist-info/RECORD
